{"data":{"site":{"siteMetadata":{"title":"SW_P","author":"BTTB66"}},"markdownRemark":{"id":"335d06a8-aa6e-50f6-9b34-1dc98ced44a8","html":"<p>기본적인 설정, 포스트 작성 예시는 Documents를 확인하세요.</p>\n<ul>\n<li><a href=\"https://github.com/junhobaik/junhobaik.github.io/wiki/Documents\">Documnets</a></li>\n<li><a href=\"https://github.com/junhobaik/junhobaik.github.io\">Github Repository</a></li>\n<li><a href=\"https://junhobaik.github.io/\">Demo blog</a></li>\n</ul>","excerpt":"기본적인 설정, 포스트 작성 예시는 Documents를 확인하세요. Documnets Github Repository Demo blog","frontmatter":{"title":"First Post, README","date":"2018-11-06","tags":["blog"],"keywords":["SW_P"]}}},"pageContext":{"slug":"/first-post/","previous":null,"next":{"fields":{"slug":"/algo-4-post/"},"frontmatter":{"title":"[BOJ 9207] 페그 솔리테어","tags":["algorithm"],"published":true}}}}